neoalchemy/__init__.py
neoalchemy/graph.py
neoalchemy/types.py
neoalchemy/cypher/__init__.py
neoalchemy/cypher/base.py
neoalchemy/schema/__init__.py
neoalchemy/schema/base.py
neoalchemy/schema/operations.py
neoalchemy/schema/orm.py
neoalchemy-0.8.0b7.dist-info/DESCRIPTION.rst
neoalchemy-0.8.0b7.dist-info/METADATA
neoalchemy-0.8.0b7.dist-info/RECORD
neoalchemy-0.8.0b7.dist-info/WHEEL
neoalchemy-0.8.0b7.dist-info/metadata.json
neoalchemy-0.8.0b7.dist-info/top_level.txt
